[
  {
    "title": "News and views (3&amp;4)",
    "url": "https://doi.org/10.1007/s43673-026-00186-w",
    "source": "AAPPS bulletin",
    "publishedAt": "2026-05-12",
    "collectedAt": "2026-05-14T08:14:34.443Z",
    "query": "lithium ion battery fast charging mechanism",
    "type": "paper",
    "review": "unreviewed",
    "topics": [
      "fast-charge"
    ],
    "companies": [],
    "technologyRoutes": [],
    "evidenceLevel": "medium"
  },
  {
    "title": "From printed architectures to functional batteries: printing technologies, post-processing, and sintering",
    "url": "https://doi.org/10.1007/s44500-026-00002-3",
    "source": "Advanced Materials Joining",
    "publishedAt": "2026-05-12",
    "collectedAt": "2026-05-14T08:14:34.443Z",
    "query": "lithium ion battery fast charging mechanism",
    "type": "paper",
    "review": "unreviewed",
    "topics": [
      "fast-charge"
    ],
    "companies": [],
    "technologyRoutes": [],
    "evidenceLevel": "medium"
  },
  {
    "title": "Multi-Model Fusion of Lithium Battery SOC Estimation Based on Bayesian Principle",
    "url": "https://doi.org/10.3390/math14101642",
    "source": "Mathematics",
    "publishedAt": "2026-05-12",
    "collectedAt": "2026-05-14T08:14:34.443Z",
    "query": "lithium ion battery fast charging mechanism",
    "type": "paper",
    "review": "unreviewed",
    "topics": [
      "fast-charge",
      "bms"
    ],
    "companies": [],
    "technologyRoutes": [],
    "evidenceLevel": "medium"
  },
  {
    "title": "A siting and sizing strategy for distribution grid energy storage systems accounting for reliability and battery lifespan",
    "url": "https://doi.org/10.3389/fenrg.2026.1755322",
    "source": "Frontiers in Energy Research",
    "publishedAt": "2026-05-12",
    "collectedAt": "2026-05-14T08:14:34.443Z",
    "query": "lithium ion battery fast charging mechanism",
    "type": "paper",
    "review": "unreviewed",
    "topics": [
      "fast-charge"
    ],
    "companies": [],
    "technologyRoutes": [],
    "evidenceLevel": "medium"
  },
  {
    "title": "Methodology for Selecting Parameters of Electric Energy Storage Systems in Microgrids with Integration of Electric Vehicle Charging Stations",
    "url": "https://doi.org/10.3390/en19102307",
    "source": "Energies",
    "publishedAt": "2026-05-11",
    "collectedAt": "2026-05-14T08:14:34.443Z",
    "query": "lithium ion battery fast charging mechanism",
    "type": "paper",
    "review": "unreviewed",
    "topics": [
      "fast-charge"
    ],
    "companies": [],
    "technologyRoutes": [],
    "evidenceLevel": "medium"
  },
  {
    "title": "Quasi-degenerate cation occupation enables nearly defect-free functional crystals",
    "url": "https://doi.org/10.21203/rs.3.rs-9624869/v1",
    "source": "Research Square",
    "publishedAt": "2026-05-11",
    "collectedAt": "2026-05-14T08:14:34.443Z",
    "query": "lithium ion battery fast charging mechanism",
    "type": "paper",
    "review": "unreviewed",
    "topics": [
      "fast-charge"
    ],
    "companies": [],
    "technologyRoutes": [],
    "evidenceLevel": "medium"
  },
  {
    "title": "Electronic Delocalization of Fe Atom–Cluster for Long-Term Stable Electromagnetic Wave Absorption in Marine Environments",
    "url": "https://doi.org/10.1007/s40820-026-02210-y",
    "source": "Nano-Micro Letters",
    "publishedAt": "2026-05-11",
    "collectedAt": "2026-05-14T08:14:34.443Z",
    "query": "sodium ion battery hard carbon review",
    "type": "paper",
    "review": "unreviewed",
    "topics": [
      "sodium-ion"
    ],
    "companies": [],
    "technologyRoutes": [
      "sodium-hard-carbon"
    ],
    "evidenceLevel": "medium"
  },
  {
    "title": "Insights into Sensing and Biomedical Domains Using Multi-Synthetic Covalent Organic Frameworks",
    "url": "https://doi.org/10.3390/bios16050280",
    "source": "Biosensors",
    "publishedAt": "2026-05-11",
    "collectedAt": "2026-05-14T08:14:34.443Z",
    "query": "sodium ion battery hard carbon review",
    "type": "paper",
    "review": "unreviewed",
    "topics": [
      "sodium-ion"
    ],
    "companies": [],
    "technologyRoutes": [
      "sodium-hard-carbon"
    ],
    "evidenceLevel": "medium"
  },
  {
    "title": "Understanding the Key Role and Evaluation Methods of Sodium Storage Behavior/Mechanisms for Hard Carbon Anode",
    "url": "https://doi.org/10.1002/ifm2.70017",
    "source": "Information & Functional Materials",
    "publishedAt": "2026-05-11",
    "collectedAt": "2026-05-14T08:14:34.443Z",
    "query": "sodium ion battery hard carbon review",
    "type": "paper",
    "review": "unreviewed",
    "topics": [
      "sodium-ion"
    ],
    "companies": [],
    "technologyRoutes": [
      "sodium-hard-carbon"
    ],
    "evidenceLevel": "medium"
  },
  {
    "title": "Progresses of Research in Anode Materials for Lithium-Ion Batteries",
    "url": "https://doi.org/10.1051/matecconf/202642001019/pdf",
    "source": "Springer Link (Chiba Institute of Technology)",
    "publishedAt": "2026-05-08",
    "collectedAt": "2026-05-14T08:14:34.443Z",
    "query": "sodium ion battery hard carbon review",
    "type": "paper",
    "review": "unreviewed",
    "topics": [
      "sodium-ion"
    ],
    "companies": [],
    "technologyRoutes": [
      "sodium-hard-carbon"
    ],
    "evidenceLevel": "medium"
  },
  {
    "title": "Towards Medium-Temperature Hydrogen Fuel Cell with Glassy Proton-Conductive Membrane—Part II: Mixed-Anion Matrices, Composites and Hybrid Systems",
    "url": "https://doi.org/10.3390/en19102254",
    "source": "Energies",
    "publishedAt": "2026-05-07",
    "collectedAt": "2026-05-14T08:14:34.443Z",
    "query": "sodium ion battery hard carbon review",
    "type": "paper",
    "review": "unreviewed",
    "topics": [
      "sodium-ion",
      "separator"
    ],
    "companies": [],
    "technologyRoutes": [
      "sodium-hard-carbon"
    ],
    "evidenceLevel": "medium"
  },
  {
    "title": "Freeze it or leave it? Evaluating the role of cryo-electron microscopy in battery research",
    "url": "https://doi.org/10.1557/s43579-026-00971-6",
    "source": "MRS Communications",
    "publishedAt": "2026-05-11",
    "collectedAt": "2026-05-14T08:14:34.443Z",
    "query": "dry electrode lithium ion battery manufacturing",
    "type": "paper",
    "review": "unreviewed",
    "topics": [
      "dry-electrode"
    ],
    "companies": [],
    "technologyRoutes": [],
    "evidenceLevel": "medium"
  },
  {
    "title": null,
    "url": "https://doi.org/10.32782/2663-5941/2026.2.2",
    "source": "Scientific notes of Taurida National V I Vernadsky University Series Technical Sciences",
    "publishedAt": "2026-05-11",
    "collectedAt": "2026-05-14T08:14:34.443Z",
    "query": "dry electrode lithium ion battery manufacturing",
    "type": "paper",
    "review": "unreviewed",
    "topics": [
      "dry-electrode"
    ],
    "companies": [],
    "technologyRoutes": [],
    "evidenceLevel": "medium"
  },
  {
    "title": "Multi-Responsive SEBS/MXene Janus Membranes Enabling Piezoelectric Energy Harvesting, Humidity Sensing, and Infrared Stealth",
    "url": "https://doi.org/10.1007/s40820-026-02184-x",
    "source": "Nano-Micro Letters",
    "publishedAt": "2026-05-11",
    "collectedAt": "2026-05-14T08:14:34.443Z",
    "query": "dry electrode lithium ion battery manufacturing",
    "type": "paper",
    "review": "unreviewed",
    "topics": [
      "dry-electrode",
      "separator"
    ],
    "companies": [],
    "technologyRoutes": [],
    "evidenceLevel": "medium"
  },
  {
    "title": "Synthesis, Characterization, and Electrochemical Evaluation of Electrodeposited NiCuZn Powders for Urea Oxidation",
    "url": "https://doi.org/10.3390/ma19101973",
    "source": "Materials",
    "publishedAt": "2026-05-10",
    "collectedAt": "2026-05-14T08:14:34.443Z",
    "query": "dry electrode lithium ion battery manufacturing",
    "type": "paper",
    "review": "unreviewed",
    "topics": [
      "dry-electrode"
    ],
    "companies": [],
    "technologyRoutes": [],
    "evidenceLevel": "medium"
  },
  {
    "title": "Half-Cell Open-Circuit Voltage of Several Lithium-Ion Battery Active Materials Measured under Various Electrochemical Protocols",
    "url": "https://doi.org/10.5281/zenodo.19107294",
    "source": "Zenodo (CERN European Organization for Nuclear Research)",
    "publishedAt": "2026-05-08",
    "collectedAt": "2026-05-14T08:14:34.443Z",
    "query": "dry electrode lithium ion battery manufacturing",
    "type": "paper",
    "review": "unreviewed",
    "topics": [
      "dry-electrode"
    ],
    "companies": [],
    "technologyRoutes": [],
    "evidenceLevel": "medium"
  },
  {
    "title": "Electrochemically-driven formation of Intermetallic Cu<sub>3</sub>ZnLi<sub>2</sub> alters Li-transport in nanostructured bimetallic battery anode",
    "url": "https://openalex.org/W7140964301",
    "source": "MPG.PuRe (Max Planck Society)",
    "publishedAt": "2026-06-01",
    "collectedAt": "2026-05-14T08:14:34.443Z",
    "query": "solid state battery electrolyte interface",
    "type": "paper",
    "review": "unreviewed",
    "topics": [
      "solid-state",
      "electrolyte",
      "bms"
    ],
    "companies": [],
    "technologyRoutes": [],
    "evidenceLevel": "medium"
  },
  {
    "title": "Revealing the Role of MOF and COF Reticular Chemistry in Solid State Batteries: From Electrode to Electrolyte Design",
    "url": "https://doi.org/10.1002/adma.73311",
    "source": "Advanced Materials",
    "publishedAt": "2026-05-12",
    "collectedAt": "2026-05-14T08:14:34.443Z",
    "query": "solid state battery electrolyte interface",
    "type": "paper",
    "review": "unreviewed",
    "topics": [
      "solid-state",
      "electrolyte"
    ],
    "companies": [],
    "technologyRoutes": [],
    "evidenceLevel": "medium"
  },
  {
    "title": "Compatible Dynamically Wetting Electrolyte–Electrode Interface Design for Solid‐State Lithium–Sulfur Batteries",
    "url": "https://doi.org/10.1002/ange.1261984",
    "source": "Angewandte Chemie",
    "publishedAt": "2026-05-12",
    "collectedAt": "2026-05-14T08:14:34.443Z",
    "query": "solid state battery electrolyte interface",
    "type": "paper",
    "review": "unreviewed",
    "topics": [
      "solid-state",
      "electrolyte"
    ],
    "companies": [],
    "technologyRoutes": [],
    "evidenceLevel": "medium"
  },
  {
    "title": "Silicon‐Based Anodes for Sulfide Solid‐State Batteries: Failure Mechanisms and Multiscale Design Strategies",
    "url": "https://doi.org/10.1002/aenm.71065",
    "source": "Advanced Energy Materials",
    "publishedAt": "2026-05-12",
    "collectedAt": "2026-05-14T08:14:34.443Z",
    "query": "solid state battery electrolyte interface",
    "type": "paper",
    "review": "unreviewed",
    "topics": [
      "solid-state",
      "electrolyte"
    ],
    "companies": [],
    "technologyRoutes": [],
    "evidenceLevel": "medium"
  },
  {
    "title": "Développement d'électrolytes polymères nanoporeux pour les batteries au lithium métal",
    "url": "https://openalex.org/W7140013056",
    "source": "HAL (Le Centre pour la Communication Scientifique Directe)",
    "publishedAt": "2026-05-20",
    "collectedAt": "2026-05-14T08:14:34.443Z",
    "query": "lithium battery separator electrolyte safety",
    "type": "paper",
    "review": "unreviewed",
    "topics": [
      "separator",
      "electrolyte"
    ],
    "companies": [],
    "technologyRoutes": [],
    "evidenceLevel": "medium"
  },
  {
    "title": "Research Progress on Graphite Anode of Lithium-ion Batteries",
    "url": "https://doi.org/10.1051/matecconf/202642001024/pdf",
    "source": "Springer Link (Chiba Institute of Technology)",
    "publishedAt": "2026-05-08",
    "collectedAt": "2026-05-14T08:14:34.443Z",
    "query": "lithium battery separator electrolyte safety",
    "type": "paper",
    "review": "unreviewed",
    "topics": [
      "separator",
      "electrolyte"
    ],
    "companies": [],
    "technologyRoutes": [],
    "evidenceLevel": "medium"
  },
  {
    "title": "Recent Advances in Phase Change Materials for Thermal Management of Lithium-Ion and Emerging X-Ion Batteries: A Review",
    "url": "https://doi.org/10.3390/sym18050803",
    "source": "Symmetry",
    "publishedAt": "2026-05-08",
    "collectedAt": "2026-05-14T08:14:34.443Z",
    "query": "lithium battery separator electrolyte safety",
    "type": "paper",
    "review": "unreviewed",
    "topics": [
      "separator",
      "electrolyte",
      "thermal-management"
    ],
    "companies": [],
    "technologyRoutes": [],
    "evidenceLevel": "medium"
  },
  {
    "title": "PAO Eco Battery: Universal Clean Energy Storage — Na‑ion Gel‑Polymer, Zn‑ion Aqueous, Quinone Flow (No Lithium, No Cobalt, No Fire)",
    "url": "https://doi.org/10.5281/zenodo.20077474",
    "source": "Zenodo (CERN European Organization for Nuclear Research)",
    "publishedAt": "2026-05-08",
    "collectedAt": "2026-05-14T08:14:34.443Z",
    "query": "lithium battery separator electrolyte safety",
    "type": "paper",
    "review": "unreviewed",
    "topics": [
      "separator",
      "electrolyte"
    ],
    "companies": [],
    "technologyRoutes": [],
    "evidenceLevel": "medium"
  }
]
